src/mdio.v
module mdio #(
    parameter PHY_ADDR = 5'b00001
)(
    input  wire        clk,
    input  wire        rst_n,
    
    input  wire        mdc_i,
    input  wire        mdio_i,
    output reg         mdio_o,
    output reg         mdio_oe,
    
    output reg  [4:0]  reg_addr,
    output reg  [15:0] reg_wdata,
    output reg         reg_write_en,
    input  wire [15:0] reg_rdata
);

    reg mdc_d, mdc_dd;
    always @(posedge clk or negedge rst_n) begin
        if (!rst_n) begin
            mdc_d <= 1'b0;
            mdc_dd <= 1'b0;
        end else begin
            mdc_dd <= mdc_d;
            mdc_d <= mdc_i;
        end
    end
    wire mdc_rise = !mdc_dd && mdc_d;
    wire mdc_fall = mdc_dd && !mdc_d;

    reg [1:0] state;
    localparam IDLE = 2'd0;
    localparam RUN = 2'd1;

    reg [5:0] bit_cnt;
    reg [5:0] ones_cnt;
    reg [13:0] header_buf; // ST(2), OP(2), PHY(5), REG(5) -> 14 bits
    reg [15:0] data_buf;

    always @(posedge clk or negedge rst_n) begin
        if (!rst_n) begin
            state <= IDLE;
            bit_cnt <= 0;
            ones_cnt <= 0;
            header_buf <= 0;
            data_buf <= 0;
            reg_addr <= 0;
            reg_wdata <= 0;
            reg_write_en <= 0;
            mdio_oe <= 0;
            mdio_o <= 0;
        end else begin
            reg_write_en <= 1'b0;

            if (mdc_rise) begin
                if (state == IDLE) begin
                    if (mdio_i == 1'b1) begin
                        if (ones_cnt < 63) ones_cnt <= ones_cnt + 1;
                    end else begin
                        if (ones_cnt >= 32) begin
                            state <= RUN;
                            bit_cnt <= 1;
                            header_buf <= 14'b0;
                        end
                        ones_cnt <= 0;
                    end
                end else if (state == RUN) begin
                    bit_cnt <= bit_cnt + 1;
                    
                    if (bit_cnt < 14) begin
                        header_buf <= {header_buf[12:0], mdio_i};
                        if (bit_cnt == 13) begin
                            reg_addr <= {header_buf[3:0], mdio_i};
                        end
                    end else if (bit_cnt >= 16) begin
                        if (header_buf[11:10] == 2'b01) begin
                            data_buf <= {data_buf[14:0], mdio_i};
                        end
                        if (bit_cnt == 31) begin
                            state <= IDLE;
                            bit_cnt <= 0;
                            if (header_buf[13:12] == 2'b01 && header_buf[11:10] == 2'b01 && header_buf[9:5] == PHY_ADDR) begin
                                reg_wdata <= {data_buf[14:0], mdio_i};
                                reg_write_en <= 1'b1;
                            end
                        end
                    end
                end
            end

            // Drive MDIO output on MDC FALLING EDGE to provide setup time for MAC
            if (mdc_fall) begin
                if (state == RUN) begin
                    if (header_buf[13:12] == 2'b01 && header_buf[11:10] == 2'b10 && header_buf[9:5] == PHY_ADDR) begin
                        if (bit_cnt == 15) begin
                            mdio_oe <= 1'b1;
                            mdio_o  <= 1'b0;
                            data_buf <= reg_rdata;
                        end else if (bit_cnt >= 16 && bit_cnt <= 31) begin
                            mdio_oe <= 1'b1;
                            mdio_o  <= data_buf[15];
                            data_buf <= {data_buf[14:0], 1'b0};
                        end else begin
                            mdio_oe <= 1'b0;
                        end
                    end else begin
                        mdio_oe <= 1'b0;
                    end
                end else begin
                    mdio_oe <= 1'b0;
                end
            end
            
        end
    end
endmodule

tb/mdio_tb.sv
`timescale 1ns/1ps

module mdio_tb;

    reg clk, rst_n;
    reg mdc_gen;
    reg mac_mdio_o, mac_mdio_oe;
    wire mdio_bus;
    
    assign mdio_bus = mac_mdio_oe ? mac_mdio_o : 1'bz;

    wire mdio_phy_o, mdio_phy_oe;
    assign mdio_bus = mdio_phy_oe ? mdio_phy_o : 1'bz;

    wire [4:0] reg_addr;
    wire [15:0] reg_wdata;
    wire reg_write_en;
    reg [15:0] reg_rdata;

    mdio #(.PHY_ADDR(5'h01)) dut (
        .clk(clk),
        .rst_n(rst_n),
        .mdc_i(mdc_gen),
        .mdio_i(mdio_bus),
        .mdio_o(mdio_phy_o),
        .mdio_oe(mdio_phy_oe),
        .reg_addr(reg_addr),
        .reg_wdata(reg_wdata),
        .reg_write_en(reg_write_en),
        .reg_rdata(reg_rdata)
    );

    always #5 clk = ~clk;
    always #200 mdc_gen = ~mdc_gen;

    task send_bit(input b);
    begin
        @(negedge mdc_gen);
        mac_mdio_oe = 1;
        mac_mdio_o = b;
    end
    endtask

    task send_z();
    begin
        @(negedge mdc_gen);
        mac_mdio_oe = 0;
    end
    endtask

    initial begin
        $dumpfile("mdio_tb.vcd");
        $dumpvars(0, mdio_tb);
        
        clk = 0; rst_n = 0; mdc_gen = 0; mac_mdio_oe = 0; mac_mdio_o = 1;
        #100 rst_n = 1;
        reg_rdata = 16'hABCD;
        
        // Preamble
        repeat(33) send_bit(1);
        
        // READ FRAME: ST=01, OP=10, PHY=00001, REG=00110
        send_bit(0); send_bit(1); // ST
        send_bit(1); send_bit(0); // OP Read
        send_bit(0); send_bit(0); send_bit(0); send_bit(0); send_bit(1); // PHY
        send_bit(0); send_bit(0); send_bit(1); send_bit(1); send_bit(0); // REG 6
        send_z(); send_z(); // TA
        repeat(16) send_z(); // Data
        
        // Preamble
        repeat(33) send_bit(1);
        
        // WRITE FRAME: ST=01, OP=01, PHY=00001, REG=00011, DATA=4321
        send_bit(0); send_bit(1); // ST
        send_bit(0); send_bit(1); // OP Write
        send_bit(0); send_bit(0); send_bit(0); send_bit(0); send_bit(1); // PHY
        send_bit(0); send_bit(0); send_bit(0); send_bit(1); send_bit(1); // REG 3
        send_bit(1); send_bit(0); // TA
        
        // DATA (0100 0011 0010 0001)
        send_bit(0); send_bit(1); send_bit(0); send_bit(0);
        send_bit(0); send_bit(0); send_bit(1); send_bit(1);
        send_bit(0); send_bit(0); send_bit(1); send_bit(0);
        send_bit(0); send_bit(0); send_bit(0); send_bit(1);
        send_z();

        #1000 $finish;
    end
endmodule

tb/mdio_tb.vcd
$date
	Mon Mar 23 09:29:10 2026
$end
$version
	Icarus Verilog
$end
$timescale
	1ps
$end
$scope module mdio_tb $end
$var wire 1 ! mdio_bus $end
$var wire 1 " reg_write_en $end
$var wire 16 # reg_wdata [15:0] $end
$var wire 5 $ reg_addr [4:0] $end
$var wire 1 % mdio_phy_oe $end
$var wire 1 & mdio_phy_o $end
$var reg 1 ' clk $end
$var reg 1 ( mac_mdio_o $end
$var reg 1 ) mac_mdio_oe $end
$var reg 1 * mdc_gen $end
$var reg 16 + reg_rdata [15:0] $end
$var reg 1 , rst_n $end
$scope module dut $end
$var wire 1 ' clk $end
$var wire 1 - mdc_fall $end
$var wire 1 * mdc_i $end
$var wire 1 . mdc_rise $end
$var wire 1 ! mdio_i $end
$var wire 16 / reg_rdata [15:0] $end
$var wire 1 , rst_n $end
$var parameter 2 0 IDLE $end
$var parameter 5 1 PHY_ADDR $end
$var parameter 2 2 RUN $end
$var reg 6 3 bit_cnt [5:0] $end
$var reg 16 4 data_buf [15:0] $end
$var reg 14 5 header_buf [13:0] $end
$var reg 1 6 mdc_d $end
$var reg 1 7 mdc_dd $end
$var reg 1 & mdio_o $end
$var reg 1 % mdio_oe $end
$var reg 6 8 ones_cnt [5:0] $end
$var reg 5 9 reg_addr [4:0] $end
$var reg 16 : reg_wdata [15:0] $end
$var reg 1 " reg_write_en $end
$var reg 2 ; state [1:0] $end
$upscope $end
$scope task send_bit $end
$var reg 1 < b $end
$upscope $end
$scope task send_z $end
$upscope $end
$upscope $end
$enddefinitions $end
$comment Show the parameter values. $end
$dumpall
b1 2
b1 1
b0 0
$end
#0
$dumpvars
x<
b0 ;
b0 :
b0 9
b0 8
07
06
b0 5
b0 4
b0 3
bx /
0.
0-
0,
bx +
0*
0)
1(
0'
0&
0%
b0 $
b0 #
0"
z!
$end
#5000
1'
#10000
0'
#15000
1'
#20000
0'
#25000
1'
#30000
0'
#35000
1'
#40000
0'
#45000
1'
#50000
0'
#55000
1'
#60000
0'
#65000
1'
#70000
0'
#75000
1'
#80000
0'
#85000
1'
#90000
0'
#95000
1'
#100000
0'
1<
b1010101111001101 +
b1010101111001101 /
1,
#105000
1'
#110000
0'
#115000
1'
#120000
0'
#125000
1'
#130000
0'
#135000
1'
#140000
0'
#145000
1'
#150000
0'
#155000
1'
#160000
0'
#165000
1'
#170000
0'
#175000
1'
#180000
0'
#185000
1'
#190000
0'
#195000
1'
#200000
0'
1*
#205000
1.
16
1'
#210000
0'
#215000
0.
17
1'
#220000
0'
#225000
1'
#230000
0'
#235000
1'
#240000
0'
#245000
1'
#250000
0'
#255000
1'
#260000
0'
#265000
1'
#270000
0'
#275000
1'
#280000
0'
#285000
1'
#290000
0'
#295000
1'
#300000
0'
#305000
1'
#310000
0'
#315000
1'
#320000
0'
#325000
1'
#330000
0'
#335000
1'
#340000
0'
#345000
1'
#350000
0'
#355000
1'
#360000
0'
#365000
1'
#370000
0'
#375000
1'
#380000
0'
#385000
1'
#390000
0'
#395000
1'
#400000
1!
1)
0'
0*
#405000
1-
06
1'
#410000
0'
#415000
0-
07
1'
#420000
0'
#425000
1'
#430000
0'
#435000
1'
#440000
0'
#445000
1'
#450000
0'
#455000
1'
#460000
0'
#465000
1'
#470000
0'
#475000
1'
#480000
0'
#485000
1'
#490000
0'
#495000
1'
#500000
0'
#505000
1'
#510000
0'
#515000
1'
#520000
0'
#525000
1'
#530000
0'
#535000
1'
#540000
0'
#545000
1'
#550000
0'
#555000
1'
#560000
0'
#565000
1'
#570000
0'
#575000
1'
#580000
0'
#585000
1'
#590000
0'
#595000
1'
#600000
0'
1*
#605000
1.
16
1'
#610000
0'
#615000
0.
17
b1 8
1'
#620000
0'
#625000
1'
#630000
0'
#635000
1'
#640000
0'
#645000
1'
#650000
0'
#655000
1'
#660000
0'
#665000
1'
#670000
0'
#675000
1'
#680000
0'
#685000
1'
#690000
0'
#695000
1'
#700000
0'
#705000
1'
#710000
0'
#715000
1'
#720000
0'
#725000
1'
#730000
0'
#735000
1'
#740000
0'
#745000
1'
#750000
0'
#755000
1'
#760000
0'
#765000
1'
#770000
0'
#775000
1'
#780000
0'
#785000
1'
#790000
0'
#795000
1'
#800000
0'
0*
#805000
1-
06
1'
#810000
0'
#815000
0-
07
1'
#820000
0'
#825000
1'
#830000
0'
#835000
1'
#840000
0'
#845000
1'
#850000
0'
#855000
1'
#860000
0'
#865000
1'
#870000
0'
#875000
1'
#880000
0'
#885000
1'
#890000
0'
#895000
1'
#900000
0'
#905000
1'
#910000
0'
#915000
1'
#920000
0'
#925000
1'
#930000
0'
#935000
1'
#940000
0'
#945000
1'
#950000
0'
#955000
1'
#960000
0'
#965000
1'
#970000
0'
#975000
1'
#980000
0'
#985000
1'
#990000
0'
#995000
1'
#1000000
0'
1*
#1005000
1.
16
1'
#1010000
0'
#1015000
0.
17
b10 8
1'
#1020000
0'
#1025000
1'
#1030000
0'
#1035000
1'
#1040000
0'
#1045000
1'
#1050000
0'
#1055000
1'
#1060000
0'
#1065000
1'
#1070000
0'
#1075000
1'
#1080000
0'
#1085000
1'
#1090000
0'
#1095000
1'
#1100000
0'
#1105000
1'
#1110000
0'
#1115000
1'
#1120000
0'
#1125000
1'
#1130000
0'
#1135000
1'
#1140000
0'
#1145000
1'
#1150000
0'
#1155000
1'
#1160000
0'
#1165000
1'
#1170000
0'
#1175000
1'
#1180000
0'
#1185000
1'
#1190000
0'
#1195000
1'
#1200000
0'
0*
#1205000
1-
06
1'
#1210000
0'
#1215000
0-
07
1'
#1220000
0'
#1225000
1'
#1230000
0'
#1235000
1'
#1240000
0'
#1245000
1'
#1250000
0'
#1255000
1'
#1260000
0'
#1265000
1'
#1270000
0'
#1275000
1'
#1280000
0'
#1285000
1'
#1290000
0'
#1295000
1'
#1300000
0'
#1305000
1'
#1310000
0'
#1315000
1'
#1320000
0'
#1325000
1'
#1330000
0'
#1335000
1'
#1340000
0'
#1345000
1'
#1350000
0'
#1355000
1'
#1360000
0'
#1365000
1'
#1370000
0'
#1375000
1'
#1380000
0'
#1385000
1'
#1390000
0'
#1395000
1'
#1400000
0'
1*
#1405000
1.
16
1'
#1410000
0'
#1415000
0.
17
b11 8
1'
#1420000
0'
#1425000
1'
#1430000
0'
#1435000
1'
#1440000
0'
#1445000
1'
#1450000
0'
#1455000
1'
#1460000
0'
#1465000
1'
#1470000
0'
#1475000
1'
#1480000
0'
#1485000
1'
#1490000
0'
#1495000
1'
#1500000
0'
#1505000
1'
#1510000
0'
#1515000
1'
#1520000
0'
#1525000
1'
#1530000
0'
#1535000
1'
#1540000
0'
#1545000
1'
#1550000
0'
#1555000
1'
#1560000
0'
#1565000
1'
#1570000
0'
#1575000
1'
#1580000
0'
#1585000
1'
#1590000
0'
#1595000
1'
#1600000
0'
0*
#1605000
1-
06
1'
#1610000
0'
#1615000
0-
07
1'
#1620000
0'
#1625000
1'
#1630000
0'
#1635000
1'
#1640000
0'
#1645000
1'
#1650000
0'
#1655000
1'
#1660000
0'
#1665000
1'
#1670000
0'
#1675000
1'
#1680000
0'
#1685000
1'
#1690000
0'
#1695000
1'
#1700000
0'
#1705000
1'
#1710000
0'
#1715000
1'
#1720000
0'
#1725000
1'
#1730000
0'
#1735000
1'
#1740000
0'
#1745000
1'
#1750000
0'
#1755000
1'
#1760000
0'
#1765000
1'
#1770000
0'
#1775000
1'
#1780000
0'
#1785000
1'
#1790000
0'
#1795000
1'
#1800000
0'
1*
#1805000
1.
16
1'
#1810000
0'
#1815000
0.
17
b100 8
1'
#1820000
0'
#1825000
1'
#1830000
0'
#1835000
1'
#1840000
0'
#1845000
1'
#1850000
0'
#1855000
1'
#1860000
0'
#1865000
1'
#1870000
0'
#1875000
1'
#1880000
0'
#1885000
1'
#1890000
0'
#1895000
1'
#1900000
0'
#1905000
1'
#1910000
0'
#1915000
1'
#1920000
0'
#1925000
1'
#1930000
0'
#1935000
1'
#1940000
0'
#1945000
1'
#1950000
0'
#1955000
1'
#1960000
0'
#1965000
1'
#1970000
0'
#1975000
1'
#1980000
0'
#1985000
1'
#1990000
0'
#1995000
1'
#2000000
0'
0*
#2005000
1-
06
1'
#2010000
0'
#2015000
0-
07
1'
#2020000
0'
#2025000
1'
#2030000
0'
#2035000
1'
#2040000
0'
#2045000
1'
#2050000
0'
#2055000
1'
#2060000
0'
#2065000
1'
#2070000
0'
#2075000
1'
#2080000
0'
#2085000
1'
#2090000
0'
#2095000
1'
#2100000
0'
#2105000
1'
#2110000
0'
#2115000
1'
#2120000
0'
#2125000
1'
#2130000
0'
#2135000
1'
#2140000
0'
#2145000
1'
#2150000
0'
#2155000
1'
#2160000
0'
#2165000
1'
#2170000
0'
#2175000
1'
#2180000
0'
#2185000
1'
#2190000
0'
#2195000
1'
#2200000
0'
1*
#2205000
1.
16
1'
#2210000
0'
#2215000
0.
17
b101 8
1'
#2220000
0'
#2225000
1'
#2230000
0'
#2235000
1'
#2240000
0'
#2245000
1'
#2250000
0'
#2255000
1'
#2260000
0'
#2265000
1'
#2270000
0'
#2275000
1'
#2280000
0'
#2285000
1'
#2290000
0'
#2295000
1'
#2300000
0'
#2305000
1'
#2310000
0'
#2315000
1'
#2320000
0'
#2325000
1'
#2330000
0'
#2335000
1'
#2340000
0'
#2345000
1'
#2350000
0'
#2355000
1'
#2360000
0'
#2365000
1'
#2370000
0'
#2375000
1'
#2380000
0'
#2385000
1'
#2390000
0'
#2395000
1'
#2400000
0'
0*
#2405000
1-
06
1'
#2410000
0'
#2415000
0-
07
1'
#2420000
0'
#2425000
1'
#2430000
0'
#2435000
1'
#2440000
0'
#2445000
1'
#2450000
0'
#2455000
1'
#2460000
0'
#2465000
1'
#2470000
0'
#2475000
1'
#2480000
0'
#2485000
1'
#2490000
0'
#2495000
1'
#2500000
0'
#2505000
1'
#2510000
0'
#2515000
1'
#2520000
0'
#2525000
1'
#2530000
0'
#2535000
1'
#2540000
0'
#2545000
1'
#2550000
0'
#2555000
1'
#2560000
0'
#2565000
1'
#2570000
0'
#2575000
1'
#2580000
0'
#2585000
1'
#2590000
0'
#2595000
1'
#2600000
0'
1*
#2605000
1.
16
1'
#2610000
0'
#2615000
0.
17
b110 8
1'
#2620000
0'
#2625000
1'
#2630000
0'
#2635000
1'
#2640000
0'
#2645000
1'
#2650000
0'
#2655000
1'
#2660000
0'
#2665000
1'
#2670000
0'
#2675000
1'
#2680000
0'
#2685000
1'
#2690000
0'
#2695000
1'
#2700000
0'
#2705000
1'
#2710000
0'
#2715000
1'
#2720000
0'
#2725000
1'
#2730000
0'
#2735000
1'
#2740000
0'
#2745000
1'
#2750000
0'
#2755000
1'
#2760000
0'
#2765000
1'
#2770000
0'
#2775000
1'
#2780000
0'
#2785000
1'
#2790000
0'
#2795000
1'
#2800000
0'
0*
#2805000
1-
06
1'
#2810000
0'
#2815000
0-
07
1'
#2820000
0'
#2825000
1'
#2830000
0'
#2835000
1'
#2840000
0'
#2845000
1'
#2850000
0'
#2855000
1'
#2860000
0'
#2865000
1'
#2870000
0'
#2875000
1'
#2880000
0'
#2885000
1'
#2890000
0'
#2895000
1'
#2900000
0'
#2905000
1'
#2910000
0'
#2915000
1'
#2920000
0'
#2925000
1'
#2930000
0'
#2935000
1'
#2940000
0'
#2945000
1'
#2950000
0'
#2955000
1'
#2960000
0'
#2965000
1'
#2970000
0'
#2975000
1'
#2980000
0'
#2985000
1'
#2990000
0'
#2995000
1'
#3000000
0'
1*
#3005000
1.
16
1'
#3010000
0'
#3015000
0.
17
b111 8
1'
#3020000
0'
#3025000
1'
#3030000
0'
#3035000
1'
#3040000
0'
#3045000
1'
#3050000
0'
#3055000
1'
#3060000
0'
#3065000
1'
#3070000
0'
#3075000
1'
#3080000
0'
#3085000
1'
#3090000
0'
#3095000
1'
#3100000
0'
#3105000
1'
#3110000
0'
#3115000
1'
#3120000
0'
#3125000
1'
#3130000
0'
#3135000
1'
#3140000
0'
#3145000
1'
#3150000
0'
#3155000
1'
#3160000
0'
#3165000
1'
#3170000
0'
#3175000
1'
#3180000
0'
#3185000
1'
#3190000
0'
#3195000
1'
#3200000
0'
0*
#3205000
1-
06
1'
#3210000
0'
#3215000
0-
07
1'
#3220000
0'
#3225000
1'
#3230000
0'
#3235000
1'
#3240000
0'
#3245000
1'
#3250000
0'
#3255000
1'
#3260000
0'
#3265000
1'
#3270000
0'
#3275000
1'
#3280000
0'
#3285000
1'
#3290000
0'
#3295000
1'
#3300000
0'
#3305000
1'
#3310000
0'
#3315000
1'
#3320000
0'
#3325000
1'
#3330000
0'
#3335000
1'
#3340000
0'
#3345000
1'
#3350000
0'
#3355000
1'
#3360000
0'
#3365000
1'
#3370000
0'
#3375000
1'
#3380000
0'
#3385000
1'
#3390000
0'
#3395000
1'
#3400000
0'
1*
#3405000
1.
16
1'
#3410000
0'
#3415000
0.
17
b1000 8
1'
#3420000
0'
#3425000
1'
#3430000
0'
#3435000
1'
#3440000
0'
#3445000
1'
#3450000
0'
#3455000
1'
#3460000
0'
#3465000
1'
#3470000
0'
#3475000
1'
#3480000
0'
#3485000
1'
#3490000
0'
#3495000
1'
#3500000
0'
#3505000
1'
#3510000
0'
#3515000
1'
#3520000
0'
#3525000
1'
#3530000
0'
#3535000
1'
#3540000
0'
#3545000
1'
#3550000
0'
#3555000
1'
#3560000
0'
#3565000
1'
#3570000
0'
#3575000
1'
#3580000
0'
#3585000
1'
#3590000
0'
#3595000
1'
#3600000
0'
0*
#3605000
1-
06
1'
#3610000
0'
#3615000
0-
07
1'
#3620000
0'
#3625000
1'
#3630000
0'
#3635000
1'
#3640000
0'
#3645000
1'
#3650000
0'
#3655000
1'
#3660000
0'
#3665000
1'
#3670000
0'
#3675000
1'
#3680000
0'
#3685000
1'
#3690000
0'
#3695000
1'
#3700000
0'
#3705000
1'
#3710000
0'
#3715000
1'
#3720000
0'
#3725000
1'
#3730000
0'
#3735000
1'
#3740000
0'
#3745000
1'
#3750000
0'
#3755000
1'
#3760000
0'
#3765000
1'
#3770000
0'
#3775000
1'
#3780000
0'
#3785000
1'
#3790000
0'
#3795000
1'
#3800000
0'
1*
#3805000
1.
16
1'
#3810000
0'
#3815000
0.
17
b1001 8
1'
#3820000
0'
#3825000
1'
#3830000
0'
#3835000
1'
#3840000
0'
#3845000
1'
#3850000
0'
#3855000
1'
#3860000
0'
#3865000
1'
#3870000
0'
#3875000
1'
#3880000
0'
#3885000
1'
#3890000
0'
#3895000
1'
#3900000
0'
#3905000
1'
#3910000
0'
#3915000
1'
#3920000
0'
#3925000
1'
#3930000
0'
#3935000
1'
#3940000
0'
#3945000
1'
#3950000
0'
#3955000
1'
#3960000
0'
#3965000
1'
#3970000
0'
#3975000
1'
#3980000
0'
#3985000
1'
#3990000
0'
#3995000
1'
#4000000
0'
0*
#4005000
1-
06
1'
#4010000
0'
#4015000
0-
07
1'
#4020000
0'
#4025000
1'
#4030000
0'
#4035000
1'
#4040000
0'
#4045000
1'
#4050000
0'
#4055000
1'
#4060000
0'
#4065000
1'
#4070000
0'
#4075000
1'
#4080000
0'
#4085000
1'
#4090000
0'
#4095000
1'
#4100000
0'
#4105000
1'
#4110000
0'
#4115000
1'
#4120000
0'
#4125000
1'
#4130000
0'
#4135000
1'
#4140000
0'
#4145000
1'
#4150000
0'
#4155000
1'
#4160000
0'
#4165000
1'
#4170000
0'
#4175000
1'
#4180000
0'
#4185000
1'
#4190000
0'
#4195000
1'
#4200000
0'
1*
#4205000
1.
16
1'
#4210000
0'
#4215000
0.
17
b1010 8
1'
#4220000
0'
#4225000
1'
#4230000
0'
#4235000
1'
#4240000
0'
#4245000
1'
#4250000
0'
#4255000
1'
#4260000
0'
#4265000
1'
#4270000
0'
#4275000
1'
#4280000
0'
#4285000
1'
#4290000
0'
#4295000
1'
#4300000
0'
#4305000
1'
#4310000
0'
#4315000
1'
#4320000
0'
#4325000
1'
#4330000
0'
#4335000
1'
#4340000
0'
#4345000
1'
#4350000
0'
#4355000
1'
#4360000
0'
#4365000
1'
#4370000
0'
#4375000
1'
#4380000
0'
#4385000
1'
#4390000
0'
#4395000
1'
#4400000
0'
0*
#4405000
1-
06
1'
#4410000
0'
#4415000
0-
07
1'
#4420000
0'
#4425000
1'
#4430000
0'
#4435000
1'
#4440000
0'
#4445000
1'
#4450000
0'
#4455000
1'
#4460000
0'
#4465000
1'
#4470000
0'
#4475000
1'
#4480000
0'
#4485000
1'
#4490000
0'
#4495000
1'
#4500000
0'
#4505000
1'
#4510000
0'
#4515000
1'
#4520000
0'
#4525000
1'
#4530000
0'
#4535000
1'
#4540000
0'
#4545000
1'
#4550000
0'
#4555000
1'
#4560000
0'
#4565000
1'
#4570000
0'
#4575000
1'
#4580000
0'
#4585000
1'
#4590000
0'
#4595000
1'
#4600000
0'
1*
#4605000
1.
16
1'
#4610000
0'
#4615000
0.
17
b1011 8
1'
#4620000
0'
#4625000
1'
#4630000
0'
#4635000
1'
#4640000
0'
#4645000
1'
#4650000
0'
#4655000
1'
#4660000
0'
#4665000
1'
#4670000
0'
#4675000
1'
#4680000
0'
#4685000
1'
#4690000
0'
#4695000
1'
#4700000
0'
#4705000
1'
#4710000
0'
#4715000
1'
#4720000
0'
#4725000
1'
#4730000
0'
#4735000
1'
#4740000
0'
#4745000
1'
#4750000
0'
#4755000
1'
#4760000
0'
#4765000
1'
#4770000
0'
#4775000
1'
#4780000
0'
#4785000
1'
#4790000
0'
#4795000
1'
#4800000
0'
0*
#4805000
1-
06
1'
#4810000
0'
#4815000
0-
07
1'
#4820000
0'
#4825000
1'
#4830000
0'
#4835000
1'
#4840000
0'
#4845000
1'
#4850000
0'
#4855000
1'
#4860000
0'
#4865000
1'
#4870000
0'
#4875000
1'
#4880000
0'
#4885000
1'
#4890000
0'
#4895000
1'
#4900000
0'
#4905000
1'
#4910000
0'
#4915000
1'
#4920000
0'
#4925000
1'
#4930000
0'
#4935000
1'
#4940000
0'
#4945000
1'
#4950000
0'
#4955000
1'
#4960000
0'
#4965000
1'
#4970000
0'
#4975000
1'
#4980000
0'
#4985000
1'
#4990000
0'
#4995000
1'
#5000000
0'
1*
#5005000
1.
16
1'
#5010000
0'
#5015000
0.
17
b1100 8
1'
#5020000
0'
#5025000
1'
#5030000
0'
#5035000
1'
#5040000
0'
#5045000
1'
#5050000
0'
#5055000
1'
#5060000
0'
#5065000
1'
#5070000
0'
#5075000
1'
#5080000
0'
#5085000
1'
#5090000
0'
#5095000
1'
#5100000
0'
#5105000
1'
#5110000
0'
#5115000
1'
#5120000
0'
#5125000
1'
#5130000
0'
#5135000
1'
#5140000
0'
#5145000
1'
#5150000
0'
#5155000
1'
#5160000
0'
#5165000
1'
#5170000
0'
#5175000
1'
#5180000
0'
#5185000
1'
#5190000
0'
#5195000
1'
#5200000
0'
0*
#5205000
1-
06
1'
#5210000
0'
#5215000
0-
07
1'
#5220000
0'
#5225000
1'
#5230000
0'
#5235000
1'
#5240000
0'
#5245000
1'
#5250000
0'
#5255000
1'
#5260000
0'
#5265000
1'
#5270000
0'
#5275000
1'
#5280000
0'
#5285000
1'
#5290000
0'
#5295000
1'
#5300000
0'
#5305000
1'
#5310000
0'
#5315000
1'
#5320000
0'
#5325000
1'
#5330000
0'
#5335000
1'
#5340000
0'
#5345000
1'
#5350000
0'
#5355000
1'
#5360000
0'
#5365000
1'
#5370000
0'
#5375000
1'
#5380000
0'
#5385000
1'
#5390000
0'
#5395000
1'
#5400000
0'
1*
#5405000
1.
16
1'
#5410000
0'
#5415000
0.
17
b1101 8
1'
#5420000
0'
#5425000
1'
#5430000
0'
#5435000
1'
#5440000
0'
#5445000
1'
#5450000
0'
#5455000
1'
#5460000
0'
#5465000
1'
#5470000
0'
#5475000
1'
#5480000
0'
#5485000
1'
#5490000
0'
#5495000
1'
#5500000
0'
#5505000
1'
#5510000
0'
#5515000
1'
#5520000
0'
#5525000
1'
#5530000
0'
#5535000
1'
#5540000
0'
#5545000
1'
#5550000
0'
#5555000
1'
#5560000
0'
#5565000
1'
#5570000
0'
#5575000
1'
#5580000
0'
#5585000
1'
#5590000
0'
#5595000
1'
#5600000
0'
0*
#5605000
1-
06
1'
#5610000
0'
#5615000
0-
07
1'
#5620000
0'
#5625000
1'
#5630000
0'
#5635000
1'
#5640000
0'
#5645000
1'
#5650000
0'
#5655000
1'
#5660000
0'
#5665000
1'
#5670000
0'
#5675000
1'
#5680000
0'
#5685000
1'
#5690000
0'
#5695000
1'
#5700000
0'
#5705000
1'
#5710000
0'
#5715000
1'
#5720000
0'
#5725000
1'
#5730000
0'
#5735000
1'
#5740000
0'
#5745000
1'
#5750000
0'
#5755000
1'
#5760000
0'
#5765000
1'
#5770000
0'
#5775000
1'
#5780000
0'
#5785000
1'
#5790000
0'
#5795000
1'
#5800000
0'
1*
#5805000
1.
16
1'
#5810000
0'
#5815000
0.
17
b1110 8
1'
#5820000
0'
#5825000
1'
#5830000
0'
#5835000
1'
#5840000
0'
#5845000
1'
#5850000
0'
#5855000
1'
#5860000
0'
#5865000
1'
#5870000
0'
#5875000
1'
#5880000
0'
#5885000
1'
#5890000
0'
#5895000
1'
#5900000
0'
#5905000
1'
#5910000
0'
#5915000
1'
#5920000
0'
#5925000
1'
#5930000
0'
#5935000
1'
#5940000
0'
#5945000
1'
#5950000
0'
#5955000
1'
#5960000
0'
#5965000
1'
#5970000
0'
#5975000
1'
#5980000
0'
#5985000
1'
#5990000
0'
#5995000
1'
#6000000
0'
0*
#6005000
1-
06
1'
#6010000
0'
#6015000
0-
07
1'
#6020000
0'
#6025000
1'
#6030000
0'
#6035000
1'
#6040000
0'
#6045000
1'
#6050000
0'
#6055000
1'
#6060000
0'
#6065000
1'
#6070000
0'
#6075000
1'
#6080000
0'
#6085000
1'
#6090000
0'
#6095000
1'
#6100000
0'
#6105000
1'
#6110000
0'
#6115000
1'
#6120000
0'
#6125000
1'
#6130000
0'
#6135000
1'
#6140000
0'
#6145000
1'
#6150000
0'
#6155000
1'
#6160000
0'
#6165000
1'
#6170000
0'
#6175000
1'
#6180000
0'
#6185000
1'
#6190000
0'
#6195000
1'
#6200000
0'
1*
#6205000
1.
16
1'
#6210000
0'
#6215000
0.
17
b1111 8
1'
#6220000
0'
#6225000
1'
#6230000
0'
#6235000
1'
#6240000
0'
#6245000
1'
#6250000
0'
#6255000
1'
#6260000
0'
#6265000
1'
#6270000
0'
#6275000
1'
#6280000
0'
#6285000
1'
#6290000
0'
#6295000
1'
#6300000
0'
#6305000
1'
#6310000
0'
#6315000
1'
#6320000
0'
#6325000
1'
#6330000
0'
#6335000
1'
#6340000
0'
#6345000
1'
#6350000
0'
#6355000
1'
#6360000
0'
#6365000
1'
#6370000
0'
#6375000
1'
#6380000
0'
#6385000
1'
#6390000
0'
#6395000
1'
#6400000
0'
0*
#6405000
1-
06
1'
#6410000
0'
#6415000
0-
07
1'
#6420000
0'
#6425000
1'
#6430000
0'
#6435000
1'
#6440000
0'
#6445000
1'
#6450000
0'
#6455000
1'
#6460000
0'
#6465000
1'
#6470000
0'
#6475000
1'
#6480000
0'
#6485000
1'
#6490000
0'
#6495000
1'
#6500000
0'
#6505000
1'
#6510000
0'
#6515000
1'
#6520000
0'
#6525000
1'
#6530000
0'
#6535000
1'
#6540000
0'
#6545000
1'
#6550000
0'
#6555000
1'
#6560000
0'
#6565000
1'
#6570000
0'
#6575000
1'
#6580000
0'
#6585000
1'
#6590000
0'
#6595000
1'
#6600000
0'
1*
#6605000
1.
16
1'
#6610000
0'
#6615000
0.
17
b10000 8
1'
#6620000
0'
#6625000
1'
#6630000
0'
#6635000
1'
#6640000
0'
#6645000
1'
#6650000
0'
#6655000
1'
#6660000
0'
#6665000
1'
#6670000
0'
#6675000
1'
#6680000
0'
#6685000
1'
#6690000
0'
#6695000
1'
#6700000
0'
#6705000
1'
#6710000
0'
#6715000
1'
#6720000
0'
#6725000
1'
#6730000
0'
#6735000
1'
#6740000
0'
#6745000
1'
#6750000
0'
#6755000
1'
#6760000
0'
#6765000
1'
#6770000
0'
#6775000
1'
