src/mdio.v
module mdio #(
    parameter PHY_ADDR = 5'b00001
)(
    input  wire        clk,
    input  wire        rst_n,
    
    input  wire        mdc_i,
    input  wire        mdio_i,
    output reg         mdio_o,
    output reg         mdio_oe,
    
    output reg  [4:0]  reg_addr,
    output reg  [15:0] reg_wdata,
    output reg         reg_write_en,
    input  wire [15:0] reg_rdata
);

    reg mdc_d, mdc_dd;
    always @(posedge clk or negedge rst_n) begin
        if (!rst_n) begin
            mdc_d <= 1'b0;
            mdc_dd <= 1'b0;
        end else begin
            mdc_dd <= mdc_d;
            mdc_d <= mdc_i;
        end
    end
    wire mdc_rise = !mdc_dd && mdc_d;
    wire mdc_fall = mdc_dd && !mdc_d;

    reg [1:0] state;
    localparam IDLE = 2'd0;
    localparam RUN = 2'd1;

    reg [5:0] bit_cnt;
    reg [5:0] ones_cnt;
    reg [13:0] header_buf; // ST(2), OP(2), PHY(5), REG(5) -> 14 bits
    reg [15:0] data_buf;

    always @(posedge clk or negedge rst_n) begin
        if (!rst_n) begin
            state <= IDLE;
            bit_cnt <= 0;
            ones_cnt <= 0;
            header_buf <= 0;
            data_buf <= 0;
            reg_addr <= 0;
            reg_wdata <= 0;
            reg_write_en <= 0;
            mdio_oe <= 0;
            mdio_o <= 0;
        end else begin
            reg_write_en <= 1'b0;

            if (mdc_rise) begin
                if (state == IDLE) begin
                    if (mdio_i == 1'b1) begin
                        if (ones_cnt < 63) ones_cnt <= ones_cnt + 1;
                    end else begin
                        if (ones_cnt >= 32) begin
                            state <= RUN;
                            bit_cnt <= 1;
                            header_buf <= 14'b0;
                        end
                        ones_cnt <= 0;
                    end
                end else if (state == RUN) begin
                    bit_cnt <= bit_cnt + 1;
                    
                    if (bit_cnt < 14) begin
                        header_buf <= {header_buf[12:0], mdio_i};
                        if (bit_cnt == 13) begin
                            reg_addr <= {header_buf[3:0], mdio_i};
                        end
                    end else if (bit_cnt >= 16) begin
                        if (header_buf[11:10] == 2'b01) begin
                            data_buf <= {data_buf[14:0], mdio_i};
                        end
                        if (bit_cnt == 31) begin
                            state <= IDLE;
                            bit_cnt <= 0;
                            if (header_buf[13:12] == 2'b01 && header_buf[11:10] == 2'b01 && header_buf[9:5] == PHY_ADDR) begin
                                reg_wdata <= {data_buf[14:0], mdio_i};
                                reg_write_en <= 1'b1;
                            end
                        end
                    end
                end
            end

            // Drive MDIO output on MDC FALLING EDGE to provide setup time for MAC
            if (mdc_fall) begin
                if (state == RUN) begin
                    if (header_buf[13:12] == 2'b01 && header_buf[11:10] == 2'b10 && header_buf[9:5] == PHY_ADDR) begin
                        if (bit_cnt == 15) begin
                            mdio_oe <= 1'b1;
                            mdio_o  <= 1'b0;
                            data_buf <= reg_rdata;
                        end else if (bit_cnt >= 16 && bit_cnt <= 31) begin
                            mdio_oe <= 1'b1;
                            mdio_o  <= data_buf[15];
                            data_buf <= {data_buf[14:0], 1'b0};
                        end else begin
                            mdio_oe <= 1'b0;
                        end
                    end else begin
                        mdio_oe <= 1'b0;
                    end
                end else begin
                    mdio_oe <= 1'b0;
                end
            end
            
        end
    end
endmodule

src/phy.v
module phy(
    input        clk,       // 100 MHz system clock
    input        rst_n,     // Reset

    input        ref_clk,   // 50 MHz RMII clock
    input        tx_en,     // Transmit Enable
    input  [1:0] txd,       // Transmit Data
    output       rx_dv,     // Receive Data Valid
    output [1:0] rxd,       // Receive Data

    input        mdc_i,     // MDC input
    output       mdc_o,     // MDC output
    output       mdc_oe,    // MDC output enable
    input        mdio_i,    // MDIO input
    output       mdio_o,    // MDIO output
    output       mdio_oe,   // MDIO output enable

    output       tx         // TX output line

);

    // Sync inputs
    reg ref_clk_d;
    reg ref_clk_dd;
    reg tx_en_d;
    reg tx_en_dd;
    reg [1:0] txd_d;
    reg [1:0] txd_dd;

    always @(posedge clk or negedge rst_n) begin // 100 MHz
        if (!rst_n) begin
            ref_clk_d <= 0;
            ref_clk_dd <= 0;
            tx_en_d <= 0;
            tx_en_dd <= 0;
            txd_d <= 2'b00;
            txd_dd <= 2'b00;
        end else begin
            ref_clk_dd <= ref_clk_d;
            ref_clk_d <= ref_clk;
            tx_en_dd <= tx_en_d;
            tx_en_d <= tx_en;
            txd_dd <= txd_d;
            txd_d <= txd;
        end
    end

    // TX logic
    reg [3:0] cycle_count;
    reg [2:0] enc_count;
    reg [3:0] enc_buf;

    always @(posedge clk or negedge rst_n) begin // 100 MHz
        if (!rst_n) begin
            cycle_count <= 9;
            enc_count <= 0;
            enc_buf <= 4'b0000;
        end else begin
            
            if (!ref_clk_dd && ref_clk_d) begin // 50 MHz rising edge
                if (tx_en_dd) begin
                    if (cycle_count >= 9) cycle_count <= 0;
                    else cycle_count <= cycle_count + 1;
                end else begin
                    cycle_count <= 9;
                end
            end

            if (!ref_clk_dd && ref_clk_d && tx_en_dd && (cycle_count >= 9)) begin
                enc_buf <= {txd_dd[1] ? 2'b10 : 2'b01, 
                            txd_dd[0] ? 2'b10 : 2'b01}; 
                enc_count <= 0;
            end else if (enc_count >= 4) begin
                enc_buf <= {enc_buf[3], enc_buf[3:1]};
                enc_count <= 0;
            end else begin
                enc_count <= enc_count + 1;
            end

        end
    end

    assign tx = enc_buf[0];



    // MDIO Submodule Instantiation
    wire [4:0]  reg_addr;
    wire [15:0] reg_wdata;
    wire        reg_write_en;
    reg  [15:0] reg_rdata;

    wire _unused_wdata = &{1'b0, reg_wdata[13:0]};

    mdio #(.PHY_ADDR(5'b00001)) mdio_inst (
        .clk(clk),
        .rst_n(rst_n),
        .mdc_i(mdc_i),
        .mdio_i(mdio_i),
        .mdio_o(mdio_o),
        .mdio_oe(mdio_oe),
        .reg_addr(reg_addr),
        .reg_wdata(reg_wdata),
        .reg_write_en(reg_write_en),
        .reg_rdata(reg_rdata)
    );

    // Register Read Multiplexer
    reg reg_loopback;
    reg [15:0] tx_packet_count;

    always @(*) begin
        case (reg_addr)
            5'd0:  reg_rdata = {1'b0, reg_loopback, 5'b00000, 1'b1, 8'b00000000}; // BMCR
            5'd1:  reg_rdata = 16'h1804; // BMSR
            5'd2:  reg_rdata = 16'h4843; // PHYID1 ("HC")
            5'd3:  reg_rdata = 16'h2025; // PHYID2 ("25")
            5'd16: reg_rdata = tx_packet_count; // Vendor Specific TX Packet Count
            default: reg_rdata = 16'h0000;
        endcase
    end

    // Register Write & Statistics Logic
    always @(posedge clk or negedge rst_n) begin // 100 MHz
        if (!rst_n) begin
            reg_loopback <= 1'b0;
            tx_packet_count <= 16'd0;
        end else begin
            if (reg_write_en && reg_addr == 5'd0) begin
                reg_loopback <= reg_wdata[14];
                if (reg_wdata[15]) begin
                    tx_packet_count <= 16'd0; // Use soft-reset to clear stats
                end
            end
            
            if (!tx_en_dd && tx_en_d) begin
                tx_packet_count <= tx_packet_count + 1;
            end
        end
    end

    // Loopback Management
    assign rx_dv = reg_loopback ? tx_en : 1'b0;
    assign rxd   = reg_loopback ? txd   : 2'b00;

    // MDC tri-state pins remain inputs
    assign mdc_o = 1'b0;
    assign mdc_oe = 1'b0;

endmodule

tb/phy_tb.sv
`timescale 1ns/1ps

module phy_tb;

    // Registers for inputs
    reg clk;
    reg rst_n;
    reg ref_clk;
    reg tx_en;
    reg [1:0] txd;
    reg mdc_i;
    reg mdio_i;

    // Wires for outputs
    wire rx_dv;
    wire [1:0] rxd;
    wire mdc_o;
    wire mdc_oe;
    wire mdio_o;
    wire mdio_oe;
    wire tx;

    // Instantiate the PHY module
    phy dut (
        .clk(clk),
        .rst_n(rst_n),
        .ref_clk(ref_clk),
        .tx_en(tx_en),
        .txd(txd),
        .rx_dv(rx_dv),
        .rxd(rxd),
        .mdc_i(mdc_i),
        .mdc_o(mdc_o),
        .mdc_oe(mdc_oe),
        .mdio_i(mdio_i),
        .mdio_o(mdio_o),
        .mdio_oe(mdio_oe),
        .tx(tx)
    );

    // 100 MHz System Clock (10ns period)
    always #5 clk = ~clk;

    // 50 MHz RMII Reference Clock derived from 100 MHz clock
    always @(posedge clk) begin
        if (!rst_n) ref_clk <= 0;
        else ref_clk <= ~ref_clk;
    end

    // Test sequence
    initial begin
        // Setup tracing for GTKWave
        $dumpfile("phy_tb.vcd");
        $dumpvars(0, phy_tb);

        // Initialize inputs
        clk = 0;
        rst_n = 0;
        tx_en = 0;
        txd = 0;
        mdc_i = 0;
        mdio_i = 0;

        // Apply reset
        #25;
        rst_n = 1;

        // Wait to observe NLP (Link Integrity Test) pulses
        $display("Observing idle state (NLP pulses should occur)...");
        #200; // Small wait just to see the beginning

        // Send a frame at 10 Mbps over 50 MHz RMII
        // Each bit of data (2 bits at a time) must be held for 10 cycles (50 MHz / 10 = 5 MHz nibble rate = 10 Mbps)
        $display("Transmitting Data...");
        
        @(negedge ref_clk);
        tx_en = 1;
        txd = 2'b01; // Data = 1
        repeat(10) @(negedge ref_clk); // Hold for 10 total cycles
        
        txd = 2'b10; // Data = 2
        repeat(10) @(negedge ref_clk);
        
        txd = 2'b11; // Data = 3
        repeat(10) @(negedge ref_clk);
        
        txd = 2'b00; // Data = 0
        repeat(10) @(negedge ref_clk);
        
        // Stop transmitting
        tx_en = 0;
        txd = 2'b00;

        // Wait a little more to see it settle back to idle
        #200;

        $display("Testbench finished.");
        $finish;
    end

endmodule

tb/phy_tb.vcd
$date
	Mon Mar 23 09:29:10 2026
$end
$version
	Icarus Verilog
$end
$timescale
	1ps
$end
$scope module phy_tb $end
$var wire 1 ! mdc_o $end
$var wire 1 " mdc_oe $end
$var wire 1 # tx $end
$var wire 2 $ rxd [1:0] $end
$var wire 1 % rx_dv $end
$var wire 1 & mdio_oe $end
$var wire 1 ' mdio_o $end
$var reg 1 ( clk $end
$var reg 1 ) mdc_i $end
$var reg 1 * mdio_i $end
$var reg 1 + ref_clk $end
$var reg 1 , rst_n $end
$var reg 1 - tx_en $end
$var reg 2 . txd [1:0] $end
$scope module dut $end
$var wire 1 ( clk $end
$var wire 1 ) mdc_i $end
$var wire 1 ! mdc_o $end
$var wire 1 " mdc_oe $end
$var wire 1 * mdio_i $end
$var wire 1 + ref_clk $end
$var wire 1 , rst_n $end
$var wire 1 - tx_en $end
$var wire 2 / txd [1:0] $end
$var wire 1 # tx $end
$var wire 2 0 rxd [1:0] $end
$var wire 1 % rx_dv $end
$var wire 1 1 reg_write_en $end
$var wire 16 2 reg_wdata [15:0] $end
$var wire 5 3 reg_addr [4:0] $end
$var wire 1 & mdio_oe $end
$var wire 1 ' mdio_o $end
$var wire 1 4 _unused_wdata $end
$var reg 4 5 cycle_count [3:0] $end
$var reg 4 6 enc_buf [3:0] $end
$var reg 3 7 enc_count [2:0] $end
$var reg 1 8 ref_clk_d $end
$var reg 1 9 ref_clk_dd $end
$var reg 1 : reg_loopback $end
$var reg 16 ; reg_rdata [15:0] $end
$var reg 1 < tx_en_d $end
$var reg 1 = tx_en_dd $end
$var reg 16 > tx_packet_count [15:0] $end
$var reg 2 ? txd_d [1:0] $end
$var reg 2 @ txd_dd [1:0] $end
$scope module mdio_inst $end
$var wire 1 ( clk $end
$var wire 1 A mdc_fall $end
$var wire 1 ) mdc_i $end
$var wire 1 B mdc_rise $end
$var wire 1 * mdio_i $end
$var wire 16 C reg_rdata [15:0] $end
$var wire 1 , rst_n $end
$var parameter 2 D IDLE $end
$var parameter 5 E PHY_ADDR $end
$var parameter 2 F RUN $end
$var reg 6 G bit_cnt [5:0] $end
$var reg 16 H data_buf [15:0] $end
$var reg 14 I header_buf [13:0] $end
$var reg 1 J mdc_d $end
$var reg 1 K mdc_dd $end
$var reg 1 ' mdio_o $end
$var reg 1 & mdio_oe $end
$var reg 6 L ones_cnt [5:0] $end
$var reg 5 M reg_addr [4:0] $end
$var reg 16 N reg_wdata [15:0] $end
$var reg 1 1 reg_write_en $end
$var reg 2 O state [1:0] $end
$upscope $end
$upscope $end
$upscope $end
$enddefinitions $end
$comment Show the parameter values. $end
$dumpall
b1 F
b1 E
b0 D
$end
#0
$dumpvars
b0 O
b0 N
b0 M
b0 L
0K
0J
b0 I
b0 H
b0 G
b100000000 C
0B
0A
b0 @
b0 ?
b0 >
0=
0<
b100000000 ;
0:
09
08
b0 7
b0 6
b1001 5
04
b0 3
b0 2
01
b0 0
b0 /
b0 .
0-
0,
x+
0*
0)
0(
0'
0&
0%
b0 $
0#
0"
0!
$end
#5000
0+
1(
#10000
0(
#15000
1(
#20000
0(
#25000
b1 7
1+
1(
1,
#30000
0(
#35000
18
b10 7
0+
1(
#40000
0(
#45000
b11 7
08
19
1+
1(
#50000
0(
#55000
18
09
b100 7
0+
1(
#60000
0(
#65000
b0 7
08
19
1+
1(
#70000
0(
#75000
18
09
b1 7
0+
1(
#80000
0(
#85000
b10 7
08
19
1+
1(
#90000
0(
#95000
18
09
b11 7
0+
1(
#100000
0(
#105000
b100 7
08
19
1+
1(
#110000
0(
#115000
18
09
b0 7
0+
1(
#120000
0(
#125000
b1 7
08
19
1+
1(
#130000
0(
#135000
18
09
b10 7
0+
1(
#140000
0(
#145000
b11 7
08
19
1+
1(
#150000
0(
#155000
18
09
b100 7
0+
1(
#160000
0(
#165000
b0 7
08
19
1+
1(
#170000
0(
#175000
18
09
b1 7
0+
1(
#180000
0(
#185000
b10 7
08
19
1+
1(
#190000
0(
#195000
18
09
b11 7
0+
1(
#200000
0(
#205000
b100 7
08
19
1+
1(
#210000
0(
#215000
18
09
b0 7
0+
1(
#220000
0(
#225000
b1 7
08
19
1+
1(
#230000
0(
#235000
b1 .
b1 /
1-
18
09
b10 7
0+
1(
#240000
0(
#245000
b11 7
b1 ?
1<
08
19
1+
1(
#250000
0(
#255000
b1 @
1=
18
09
b100 7
b1 >
0+
1(
#260000
0(
#265000
b0 7
b110 6
b0 5
08
19
1+
1(
#270000
0(
#275000
18
09
b1 7
0+
1(
#280000
0(
#285000
b10 7
b1 5
08
19
1+
1(
#290000
0(
#295000
18
09
b11 7
0+
1(
#300000
0(
#305000
b100 7
b10 5
08
19
1+
1(
#310000
0(
#315000
1#
18
09
b0 7
b11 6
0+
1(
#320000
0(
#325000
b1 7
b11 5
08
19
1+
1(
#330000
0(
#335000
18
09
b10 7
0+
1(
#340000
0(
#345000
b11 7
b100 5
08
19
1+
1(
#350000
0(
#355000
18
09
b100 7
0+
1(
#360000
0(
#365000
b0 7
b1 6
b101 5
08
19
1+
1(
#370000
0(
#375000
18
09
b1 7
0+
1(
#380000
0(
#385000
b10 7
b110 5
08
19
1+
1(
#390000
0(
#395000
18
09
b11 7
0+
1(
#400000
0(
#405000
b100 7
b111 5
08
19
1+
1(
#410000
0(
#415000
0#
18
09
b0 7
b0 6
0+
1(
#420000
0(
#425000
b1 7
b1000 5
08
19
1+
1(
#430000
0(
#435000
b10 .
b10 /
18
09
b10 7
0+
1(
#440000
0(
#445000
b11 7
b1001 5
b10 ?
08
19
1+
1(
#450000
0(
#455000
b10 @
18
09
b100 7
0+
1(
#460000
0(
#465000
1#
b0 7
b1001 6
b0 5
08
19
1+
1(
#470000
0(
#475000
18
09
b1 7
0+
1(
#480000
0(
#485000
b10 7
b1 5
08
19
1+
1(
#490000
0(
#495000
18
09
b11 7
0+
1(
#500000
0(
#505000
b100 7
b10 5
08
19
1+
1(
#510000
0(
#515000
0#
18
09
b0 7
b1100 6
0+
1(
#520000
0(
#525000
b1 7
b11 5
08
19
1+
1(
#530000
0(
#535000
18
09
b10 7
0+
1(
#540000
0(
#545000
b11 7
b100 5
08
19
1+
1(
#550000
0(
#555000
18
09
b100 7
0+
1(
#560000
0(
#565000
b0 7
b1110 6
b101 5
08
19
1+
1(
#570000
0(
#575000
18
09
b1 7
0+
1(
#580000
0(
#585000
b10 7
b110 5
08
19
1+
1(
#590000
0(
#595000
18
09
b11 7
0+
1(
#600000
0(
#605000
b100 7
b111 5
08
19
1+
1(
#610000
0(
#615000
1#
18
09
b0 7
b1111 6
0+
1(
#620000
0(
#625000
b1 7
b1000 5
08
19
1+
1(
#630000
0(
#635000
b11 .
b11 /
18
09
b10 7
0+
1(
#640000
0(
#645000
b11 7
b1001 5
b11 ?
08
19
1+
1(
#650000
0(
#655000
b11 @
18
09
b100 7
0+
1(
#660000
0(
#665000
0#
b0 7
b1010 6
b0 5
08
19
1+
1(
#670000
0(
#675000
18
09
b1 7
0+
1(
#680000
0(
#685000
b10 7
b1 5
08
19
1+
1(
#690000
0(
#695000
18
09
b11 7
0+
1(
#700000
0(
#705000
b100 7
b10 5
08
19
1+
1(
#710000
0(
#715000
1#
18
09
b0 7
b1101 6
0+
1(
#720000
0(
#725000
b1 7
b11 5
08
19
1+
1(
#730000
0(
#735000
18
09
b10 7
0+
1(
#740000
0(
#745000
b11 7
b100 5
08
19
1+
1(
#750000
0(
#755000
18
09
b100 7
0+
1(
#760000
0(
#765000
0#
b0 7
b1110 6
b101 5
08
19
1+
1(
#770000
0(
#775000
18
09
b1 7
0+
1(
#780000
0(
#785000
b10 7
b110 5
08
19
1+
1(
#790000
0(
#795000
18
09
b11 7
0+
1(
#800000
0(
#805000
b100 7
b111 5
08
19
1+
1(
#810000
0(
#815000
1#
18
09
b0 7
b1111 6
0+
1(
#820000
0(
#825000
b1 7
b1000 5
08
19
1+
1(
#830000
0(
#835000
b0 .
b0 /
18
09
b10 7
0+
1(
#840000
0(
#845000
b11 7
b1001 5
b0 ?
08
19
1+
1(
#850000
0(
#855000
b0 @
18
09
b100 7
0+
1(
#860000
0(
#865000
b0 7
b101 6
b0 5
08
19
1+
1(
#870000
0(
#875000
18
09
b1 7
0+
1(
#880000
0(
#885000
b10 7
b1 5
08
19
1+
1(
#890000
0(
#895000
18
09
b11 7
0+
1(
#900000
0(
#905000
b100 7
b10 5
08
19
1+
1(
#910000
0(
#915000
0#
18
09
b0 7
b10 6
0+
1(
#920000
0(
#925000
b1 7
b11 5
08
19
1+
1(
#930000
0(
#935000
18
09
b10 7
0+
1(
#940000
0(
#945000
b11 7
b100 5
08
19
1+
1(
#950000
0(
#955000
18
09
b100 7
0+
1(
#960000
0(
#965000
1#
b0 7
b1 6
b101 5
08
19
1+
1(
#970000
0(
#975000
18
09
b1 7
0+
1(
#980000
0(
#985000
b10 7
b110 5
08
19
1+
1(
#990000
0(
#995000
18
09
b11 7
0+
1(
#1000000
0(
#1005000
b100 7
b111 5
08
19
1+
1(
#1010000
0(
#1015000
0#
18
09
b0 7
b0 6
0+
1(
#1020000
0(
#1025000
b1 7
b1000 5
08
19
1+
1(
#1030000
0(
#1035000
0-
18
09
b10 7
0+
1(
#1040000
0(
#1045000
b11 7
b1001 5
0<
08
19
1+
1(
#1050000
0(
#1055000
0=
18
09
b100 7
0+
1(
#1060000
0(
#1065000
b0 7
08
19
1+
1(
#1070000
0(
#1075000
18
09
b1 7
0+
1(
#1080000
0(
#1085000
b10 7
08
19
1+
1(
#1090000
0(
#1095000
18
09
b11 7
0+
1(
#1100000
0(
#1105000
b100 7
08
19
1+
1(
#1110000
0(
#1115000
18
09
b0 7
0+
1(
#1120000
0(
#1125000
b1 7
08
19
1+
1(
#1130000
0(
#1135000
18
09
b10 7
0+
1(
#1140000
0(
#1145000
b11 7
08
19
1+
1(
#1150000
0(
#1155000
18
09
b100 7
0+
1(
#1160000
0(
#1165000
b0 7
08
19
1+
1(
#1170000
0(
#1175000
18
09
b1 7
0+
1(
#1180000
0(
#1185000
b10 7
08
19
1+
1(
#1190000
0(
#1195000
18
09
b11 7
0+
1(
#1200000
0(
#1205000
b100 7
08
19
1+
1(
#1210000
0(
#1215000
18
09
b0 7
0+
1(
#1220000
0(
#1225000
b1 7
08
19
1+
1(
#1230000
0(
#1235000
18
09
b10 7
0+
1(
